xy_django_model/__init__.py
xy_django_model/model.py
xy_django_model-1.0.0.dist-info/licenses/LICENSE
xy_django_model-1.0.0.dist-info/METADATA
xy_django_model-1.0.0.dist-info/WHEEL
xy_django_model-1.0.0.dist-info/top_level.txt
xy_django_model-1.0.0.dist-info/RECORD
