Metadata-Version: 2.4
Name: xy_django_model
Version: 1.0.0
Summary: Django模型的一些工具.
Author-email: 余洋 <yuyangit.0515@qq.com>
Classifier: Programming Language :: Python :: 3
Requires-Python: >=3.11.3
License-File: LICENSE
Requires-Dist: django
Dynamic: license-file
